MANIFEST.in
README.md
setup.py
django_synchroniser.egg-info/PKG-INFO
django_synchroniser.egg-info/SOURCES.txt
django_synchroniser.egg-info/dependency_links.txt
django_synchroniser.egg-info/requires.txt
django_synchroniser.egg-info/top_level.txt
example/__init__.py
example/settings.py
example/urls.py
example/wsgi.py
synchronise/__init__.py
synchronise/admin.py
synchronise/models.py
synchronise/synchronise.py
synchronise/tests.py
synchronise/urls.py
synchronise/views.py