Metadata-Version: 1.1
Name: django-synchroniser
Version: 0.2.0
Summary: django-synchroniser automagically synchronises Bitbucket Mecurial base projects to GitHub (Git based) projects
Home-page: https://github.com/elevenbits/django-synchroniser
Author: Jan Willems
Author-email: jw@elevenbits.com
License: GPLv3
Keywords: synchronise bitbucket github
Platform: UNKNOWN
Classifier: Development Status :: 4 - Beta
Classifier: Framework :: Django
Classifier: Intended Audience :: Developers
Classifier: License :: OSI Approved :: GNU General Public License v3 (GPLv3)
Classifier: Operating System :: OS Independent
Classifier: Topic :: Internet :: WWW/HTTP
Classifier: Programming Language :: Python :: 3.2
Classifier: Programming Language :: Python :: 3.3
Classifier: Programming Language :: Python :: 3.4
